safebooru2/__init__.py
safebooru2/__main__.py
safebooru2/safebooru.py
safebooru2-1.0.1.dist-info/LICENSE
safebooru2-1.0.1.dist-info/METADATA
safebooru2-1.0.1.dist-info/WHEEL
safebooru2-1.0.1.dist-info/top_level.txt
safebooru2-1.0.1.dist-info/RECORD
