Metadata-Version: 2.1
Name: safebooru2
Version: 1.0.1
Summary: Synchronous API wrapper module for safebooru.orgimplemented in Python3. 
Author: boddz
Author-email: boddz.dev@gmail.com
License: The GNU General Public License v3.0
Project-URL: GitHub, https://github.com/boddz/safebooru2
License-File: LICENSE
Requires-Dist: certifi (==2022.12.7)
Requires-Dist: charset-normalizer (==2.1.1)
Requires-Dist: idna (==3.4)
Requires-Dist: requests (==2.28.1)
Requires-Dist: urllib3 (==1.26.13)
Requires-Dist: xmltodict (==0.13.0)
